MANIFEST.in
README.rst
setup.cfg
setup.py
teststar/__init__.py
teststar/__main__.py
teststar/app.py
teststar/command.py
teststar/events.py
teststar/models.py
teststar/settings.py
teststar/state.py
teststar/tasks.py
teststar/urls.py
teststar.egg-info/PKG-INFO
teststar.egg-info/SOURCES.txt
teststar.egg-info/dependency_links.txt
teststar.egg-info/entry_points.txt
teststar.egg-info/requires.txt
teststar.egg-info/top_level.txt
teststar/api/__init__.py
teststar/api/control.py
teststar/api/events.py
teststar/api/tasks.py
teststar/api/workers.py
teststar/static/css/bootstrap-responsive.css
teststar/static/css/bootstrap-responsive.min.css
teststar/static/css/bootstrap.css
teststar/static/css/bootstrap.min.css
teststar/static/css/flower.css
teststar/static/css/jquery-ui.css
teststar/static/css/rickshaw.min.css
teststar/static/css/teststar.css
teststar/static/img/apple-touch-icon-114-precomposed.png
teststar/static/img/apple-touch-icon-144-precomposed.png
teststar/static/img/apple-touch-icon-57-precomposed.png
teststar/static/img/apple-touch-icon-72-precomposed.png
teststar/static/img/glyphicons-halflings-white.png
teststar/static/img/glyphicons-halflings.png
teststar/static/js/bootstrap-alert.js
teststar/static/js/bootstrap-button.js
teststar/static/js/bootstrap-carousel.js
teststar/static/js/bootstrap-collapse.js
teststar/static/js/bootstrap-dropdown.js
teststar/static/js/bootstrap-modal.js
teststar/static/js/bootstrap-popover.js
teststar/static/js/bootstrap-scrollspy.js
teststar/static/js/bootstrap-tab.js
teststar/static/js/bootstrap-tooltip.js
teststar/static/js/bootstrap-transition.js
teststar/static/js/bootstrap-typeahead.js
teststar/static/js/bootstrap.js
teststar/static/js/bootstrap.min.js
teststar/static/js/d3.layout.min.js
teststar/static/js/d3.min.js
teststar/static/js/flower.js
teststar/static/js/jquery-1.7.2.min.js
teststar/static/js/jquery-ui-1-8-15.min.js
teststar/static/js/rickshaw.min.js
teststar/static/js/teststar.js
teststar/templates/404.html
teststar/templates/base.html
teststar/templates/broker.html
teststar/templates/error.html
teststar/templates/monitor.html
teststar/templates/navbar.html
teststar/templates/task.html
